pywe_menu/__init__.py
pywe_menu/pywemenu.py
pywe_menu-1.0.0.dist-info/DESCRIPTION.rst
pywe_menu-1.0.0.dist-info/METADATA
pywe_menu-1.0.0.dist-info/RECORD
pywe_menu-1.0.0.dist-info/WHEEL
pywe_menu-1.0.0.dist-info/metadata.json
pywe_menu-1.0.0.dist-info/top_level.txt
