Metadata-Version: 2.0
Name: pywe-menu
Version: 1.0.0
Summary: Wechat Menu Module for Python.
Home-page: https://github.com/sdkwe/pywe-menu
Author: Hackathon
Author-email: kimi.huang@brightcells.com
License: UNKNOWN
Keywords: Wechat Weixin Menu
Platform: UNKNOWN
Classifier: License :: OSI Approved :: BSD License
Classifier: Programming Language :: Python
Classifier: Programming Language :: Python :: 2
Classifier: Programming Language :: Python :: 2.6
Classifier: Programming Language :: Python :: 2.7
Classifier: Programming Language :: Python :: 3
Classifier: Programming Language :: Python :: 3.2
Classifier: Programming Language :: Python :: 3.3
Classifier: Programming Language :: Python :: 3.4
Classifier: Topic :: Software Development :: Libraries :: Python Modules
Requires-Dist: pywe-base (>=1.0.7)
Requires-Dist: pywe-token (>=1.0.6)
